src/ABI_class.py
src/__init__.py
src/get_all_files.py
src/main.py
src/sol_to_json.py
src/templating_logic.py
eclair_cli-1.0.5.dist-info/METADATA
eclair_cli-1.0.5.dist-info/WHEEL
eclair_cli-1.0.5.dist-info/entry_points.txt
eclair_cli-1.0.5.dist-info/top_level.txt
eclair_cli-1.0.5.dist-info/RECORD
