Metadata-Version: 2.1
Name: eclair-cli
Version: 1.0.5
Summary: A tool to create library wrappers for Blockchain Business Logic code.
Home-page: https://github.com/abhinavmir/eclair
Author: August Radjoe
Author-email: atg271@gmail.com
Requires-Dist: jinja2
Requires-Dist: web3
